genomedata/__init__.py
genomedata/_bigwig.py
genomedata/_c_load_data.abi3.so
genomedata/_chromosome.py
genomedata/_close_data.py
genomedata/_erase_data.py
genomedata/_hardmask.py
genomedata/_hardmask_parsers.py
genomedata/_hdf5.py
genomedata/_histogram.py
genomedata/_info.py
genomedata/_load_data.py
genomedata/_load_seq.py
genomedata/_open_data.py
genomedata/_query.py
genomedata/_report.py
genomedata/_util.py
genomedata/load_genomedata.py
genomedata.libs/libaec-91f0ca0f.so.0.0.8
genomedata.libs/libhdf5-b5e70f84.so.103.1.0
genomedata.libs/libsz-0deeef7d.so.2.0.1
genomedata-1.7.4.dist-info/METADATA
genomedata-1.7.4.dist-info/WHEEL
genomedata-1.7.4.dist-info/entry_points.txt
genomedata-1.7.4.dist-info/top_level.txt
genomedata-1.7.4.dist-info/RECORD
genomedata-1.7.4.dist-info/licenses/LICENSE
