Metadata-Version: 2.4
Name: genomedata
Version: 1.7.4
Summary: tools for accessing large amounts of genomic data
Author-email: Michael Hoffman <michael.hoffman@utoronto.ca>
License: GPL-2.0-only
Project-URL: Bug Tracker, https://github.com/hoffmangroup/genomedata/issues
Project-URL: Download, https://pypi.python.org/pypi/genomedata
Project-URL: Homepage, https://hoffmanlab.org/proj/genomedata
Classifier: Natural Language :: English
Classifier: Development Status :: 5 - Production/Stable
Classifier: Intended Audience :: Science/Research
Classifier: License :: OSI Approved :: GNU General Public License v2 (GPLv2)
Classifier: Topic :: Scientific/Engineering :: Bio-Informatics
Classifier: Operating System :: Unix
Classifier: Programming Language :: Python :: 3
Requires-Python: >=3.10
License-File: LICENSE
Requires-Dist: numpy
Requires-Dist: tables!=3.4.1,>=3.0
Requires-Dist: six
Requires-Dist: textinput>=0.2.0
Requires-Dist: path>=16.12
Requires-Dist: pybigwig
Dynamic: license-file
